MANIFEST.in
README.md
requirements.txt
setup.py
bmm/__init__.py
bmm.egg-info/PKG-INFO
bmm.egg-info/SOURCES.txt
bmm.egg-info/dependency_links.txt
bmm.egg-info/requires.txt
bmm.egg-info/top_level.txt
bmm/src/inference/backward.py
bmm/src/inference/model.py
bmm/src/inference/parameters.py
bmm/src/inference/particles.py
bmm/src/inference/proposal.py
bmm/src/inference/resampling.py
bmm/src/inference/sample.py
bmm/src/inference/smc.py
bmm/src/tools/edges.py
bmm/src/tools/plot.py
docs/conf.py
simulations/sanity_check.py
simulations/cambridge/simulated_parameter_training.py
simulations/cambridge/single_route_ffbsi.py
simulations/cambridge/utils.py
simulations/porto/arbitrary_stitch_comp.py
simulations/porto/bulk_map_match.py
simulations/porto/max_rejections_compare.py
simulations/porto/parameter_training.py
simulations/porto/total_variation_compare.py
simulations/porto/utils.py
tests/test_MMParticles.py
tests/test_resampling.py
tests/test_smc.py