Metadata-Version: 2.1
Name: bmm
Version: 1.3
Summary: Bayesian Map-matching
Home-page: http://github.com/SamDuffield/bmm
Author: Sam Duffield
Author-email: sddd2@cam.ac.uk
License: UNKNOWN
Platform: any
Classifier: Programming Language :: Python :: 3.8
